README.md
setup.cfg
setup.py
pykintone/__init__.py
pykintone/account.py
pykintone/application.py
pykintone/base_api.py
pykintone/comment.py
pykintone/comment_api.py
pykintone/comment_result.py
pykintone/model.py
pykintone/model_result.py
pykintone/result.py
pykintone/structure.py
pykintone/structure_field.py
pykintone.egg-info/PKG-INFO
pykintone.egg-info/SOURCES.txt
pykintone.egg-info/dependency_links.txt
pykintone.egg-info/requires.txt
pykintone.egg-info/top_level.txt
pykintone/application_settings/__init__.py
pykintone/application_settings/administrator.py
pykintone/application_settings/base_administration_api.py
pykintone/application_settings/form.py
pykintone/application_settings/form_field.py
pykintone/application_settings/form_layout.py
pykintone/application_settings/general_settings.py
pykintone/application_settings/setting_result.py
pykintone/application_settings/view.py
pykintone/user_api/__init__.py
pykintone/user_api/export.py
pykintone/user_api/group.py
pykintone/user_api/organization.py
pykintone/user_api/title.py
pykintone/user_api/user.py
pykintone/user_api/user_api_result.py