Metadata-Version: 1.0
Name: pykintone
Version: 0.3.10
Summary: Python library to access kintone
Home-page: https://github.com/icoxfog417/pykintone
Author: icoxfog417
Author-email: icoxfog417@yahoo.co.jp
License: UNKNOWN
Keywords: kintone
Platform: UNKNOWN
